README
setup.py
django_staticpages.egg-info/PKG-INFO
django_staticpages.egg-info/SOURCES.txt
django_staticpages.egg-info/dependency_links.txt
django_staticpages.egg-info/top_level.txt
staticpages/__init__.py
staticpages/models.py
staticpages/urls.py
staticpages/views.py
staticpages/templatetags/__init__.py
staticpages/templatetags/staticpages_tags.py
staticpages/tests/__init__.py
staticpages/tests/test_urls.py
staticpages/tests/urls.py