Metadata-Version: 1.0
Name: django-staticpages
Version: 0.2.3
Summary: UNKNOWN
Home-page: http://github.org/gabrielgrant/django-staticpages/
Author: Gabriel Grant
Author-email: g@briel.ca
License: LGPL
Platform: UNKNOWN
